_CAL/Anniversary.py
_CAL/Appointment.py
_CAL/Calendar.py
_CAL/Date.py
_CAL/Date_Time.py
_CAL/Day_Rule.py
_CAL/Delta.py
_CAL/Formatter_Scope.py
_CAL/G8R.py
_CAL/Holiday.py
_CAL/JD.py
_CAL/LICENSE
_CAL/Ordinal.py
_CAL/Period.py
_CAL/Plan.py
_CAL/README.rst
_CAL/Range_DT.py
_CAL/Relative_Delta.py
_CAL/Scheduled.py
_CAL/TaT.py
_CAL/Time.py
_CAL/VERSION.py
_CAL/Year.py
_CAL/_DTW_.py
_CAL/__init__.py
_CAL/babel.cfg
_CAL/date_time_localizer.py
_CAL/filter_str_dates.py
_CAL/pdf.py
_CAL/setup.cfg
_CAL/setup.py
_CAL/ui_display.py
_CAL/-I18N/de.po
_CAL/-I18N/en.po
_CAL/-I18N/pt.po
_CAL/-I18N/template.pot
CAL-3.9.dist-info/LICENSE
CAL-3.9.dist-info/METADATA
CAL-3.9.dist-info/WHEEL
CAL-3.9.dist-info/top_level.txt
CAL-3.9.dist-info/RECORD
