Metadata-Version: 2.1
Name: CAL
Version: 3.9
Summary: Package dealing with date, time, and calendars.
Home-page: https://codeberg.org/tanzer/tapyr
Author: Christian Tanzer
Author-email: tanzer@swing.co.at
License: BSD License
Platform: Any
Classifier: Development Status :: 5 - Production/Stable
Classifier: License :: OSI Approved :: BSD License
Classifier: Operating System :: OS Independent
Classifier: Programming Language :: Python
Classifier: Intended Audience :: Developers
Classifier: Topic :: Software Development :: Libraries :: Python Modules
Requires-Python: >=3.9
License-File: LICENSE
Requires-Dist: TFL (>=3)
Requires-Dist: python-dateutil
Provides-Extra: icalendar
Requires-Dist: icalendar ; extra == 'icalendar'
Provides-Extra: pdf
Requires-Dist: reportlab ; extra == 'pdf'
